{
    "answer_html": "<p>so that if we wanted the <em>n</em><sup>th</sup> transition probabilities we&#8217;d have <strong>t<sub>n</sub></strong> = <em>P<sup>n</sup></em> <strong>x</strong>.</p>\n", 
    "answer_latex": "so that if we wanted the \\emph{n}\\textsuperscript{th} transition\nprobabilities we'd have \\textbf{t\\textsubscript{n}} =\n\\emph{P\\textsuperscript{n}} \\textbf{x}.", 
    "contributors": [
        "Konradbe", 
        "CarmenBruni", 
        "DavidKohler"
    ], 
    "course": "MATH152", 
    "flags": [
        "QGQ", 
        "QGH", 
        "QGS", 
        "CT"
    ], 
    "hints_html": [
        "<p>We know that if we start from <strong>x</strong> then P<strong>x</strong> gives us the probability of 1 transition. How do we get to two transitions?</p>\n"
    ], 
    "hints_latex": [
        "We know that if we start from \\textbf{x} then P\\textbf{x} gives us the\nprobability of 1 transition. How do we get to two transitions?"
    ], 
    "hints_raw": [
        "We know that if we start from '''x''' then P'''x''' gives us the probability of 1 transition.  How do we get to two transitions?\n"
    ], 
    "num_votes": 2, 
    "question": "A 23", 
    "rating": 91, 
    "sols_html": [
        "<p>We are starting in state 2 so there is 100% probability of starting in state 2 and zero elsewhere, therefore our input vector is</p>\n<p><span class=\"math\">\\[\\begin{aligned}\n\\mathbf{x}=\\left[0,1,0\\right].\\end{aligned}\\]</span></p>\n<p>If we wanted to know the probabilities for moving one transition we would compute <strong>t<sub>1</sub></strong> = <em>P<strong>x</strong></em>,</p>\n<p><span class=\"math\">\\[\\begin{aligned}\n\\mathbf{t}_1=P\\mathbf{x}=\\begin{bmatrix}\n8/10  &amp;  3/10  &amp;  1/10\\\\\n2/10  &amp;  3/10  &amp;  7/10\\\\\n0  &amp;  4/10  &amp;  2/10\n\\end{bmatrix}\n\\begin{bmatrix}\n0\\\\\n1\\\\\n0\n\\end{bmatrix}\n=\\begin{bmatrix}\n3/10\\\\\n3/10\\\\\n4/10\n\\end{bmatrix}.\\end{aligned}\\]</span></p>\n<p>However we want to know the probabilities for a second transition. We can think of this as a first transition of our new vector <strong>t<sub>1</sub></strong>. Therefore the second transition probabilities are <strong>t<sub>1</sub></strong> = <em>P</em> <strong>t<sub>1</sub></strong>,</p>\n<p><span class=\"math\">\\[\\begin{aligned}\n\\mathbf{t}_2=P\\mathbf{t}_1=\\begin{bmatrix}\n8/10  &amp;  3/10  &amp;  1/10\\\\\n2/10  &amp;  3/10  &amp;  7/10\\\\\n0  &amp;  4/10  &amp;  2/10\n\\end{bmatrix}\n\\begin{bmatrix}\n3/10\\\\\n3/10\\\\\n4/10\n\\end{bmatrix}\n=\\begin{bmatrix}\n37/100\\\\\n43/100\\\\\n20/100\n\\end{bmatrix}.\\end{aligned}\\]</span></p>\n<p>Therefore, starting in state 2, it is <strong>most likely that after two transitions, the person will still be in state 2</strong> since 43/100 is the highest of the three probabilities.</p>\n<p>Notice, we could also think of the problem as,</p>\n<p><span class=\"math\">\\[\\begin{aligned}\n\\mathbf{t}_2=P\\mathbf{t}_1=P(P\\mathbf{x})=P^2\\mathbf{x}\\end{aligned}\\]</span></p>\n<p>so that if we wanted the <em>n</em><sup>th</sup> transition probabilities we&#8217;d have <strong>t<sub>n</sub></strong> = <em>P<sup>n</sup></em> <strong>x</strong>.</p>\n"
    ], 
    "sols_latex": [
        "We are starting in state 2 so there is 100\\% probability of starting in\nstate 2 and zero elsewhere, therefore our input vector is\n\n\\begin{align*}\n\\mathbf{x}=\\left[0,1,0\\right].\n\\end{align*}\n\nIf we wanted to know the probabilities for moving one transition we\nwould compute \\textbf{t\\textsubscript{1}} = \\emph{P\\textbf{x}},\n\n\\begin{align*}\n\\mathbf{t}_1=P\\mathbf{x}=\\begin{bmatrix}\n8/10  &  3/10  &  1/10\\\\\n2/10  &  3/10  &  7/10\\\\\n0  &  4/10  &  2/10\n\\end{bmatrix}\n\\begin{bmatrix}\n0\\\\\n1\\\\\n0\n\\end{bmatrix}\n=\\begin{bmatrix}\n3/10\\\\\n3/10\\\\\n4/10\n\\end{bmatrix}.\n\\end{align*}\n\nHowever we want to know the probabilities for a second transition. We\ncan think of this as a first transition of our new vector\n\\textbf{t\\textsubscript{1}}. Therefore the second transition\nprobabilities are \\textbf{t\\textsubscript{1}} = \\emph{P}\n\\textbf{t\\textsubscript{1}},\n\n\\begin{align*}\n\\mathbf{t}_2=P\\mathbf{t}_1=\\begin{bmatrix}\n8/10  &  3/10  &  1/10\\\\\n2/10  &  3/10  &  7/10\\\\\n0  &  4/10  &  2/10\n\\end{bmatrix}\n\\begin{bmatrix}\n3/10\\\\\n3/10\\\\\n4/10\n\\end{bmatrix}\n=\\begin{bmatrix}\n37/100\\\\\n43/100\\\\\n20/100\n\\end{bmatrix}.\n\\end{align*}\n\nTherefore, starting in state 2, it is \\textbf{most likely that after two\ntransitions, the person will still be in state 2} since 43/100 is the\nhighest of the three probabilities.\n\nNotice, we could also think of the problem as,\n\n\\begin{align*}\n\\mathbf{t}_2=P\\mathbf{t}_1=P(P\\mathbf{x})=P^2\\mathbf{x}\n\\end{align*}\n\nso that if we wanted the \\emph{n}\\textsuperscript{th} transition\nprobabilities we'd have \\textbf{t\\textsubscript{n}} =\n\\emph{P\\textsuperscript{n}} \\textbf{x}."
    ], 
    "sols_raw": [
        "We are starting in state 2 so there is 100% probability of starting in state 2 and zero elsewhere, therefore our input vector is\n\n:&lt;math>\n\\mathbf{x}=\\left[0,1,0\\right].\n&lt;/math>\n\nIf we wanted to know the probabilities for moving one transition we would compute '''t&lt;sub>1&lt;/sub>''' = ''P'''x''''',\n\n:&lt;math>\n\\mathbf{t}_1=P\\mathbf{x}=\\begin{bmatrix}\n8/10  &amp;  3/10  &amp;  1/10\\\\\n2/10  &amp;  3/10  &amp;  7/10\\\\\n0  &amp;  4/10  &amp;  2/10\n\\end{bmatrix}\n\\begin{bmatrix}\n0\\\\\n1\\\\\n0\n\\end{bmatrix}\n=\\begin{bmatrix}\n3/10\\\\\n3/10\\\\\n4/10\n\\end{bmatrix}.\n&lt;/math>\n\nHowever we want to know the probabilities for a second transition.  We can think of this as a first transition of our new vector '''t&lt;sub>1&lt;/sub>'''.  Therefore the second transition probabilities are '''t&lt;sub>1&lt;/sub>''' = ''P'' '''t&lt;sub>1&lt;/sub>''',\n\n:&lt;math>\n\\mathbf{t}_2=P\\mathbf{t}_1=\\begin{bmatrix}\n8/10  &amp;  3/10  &amp;  1/10\\\\\n2/10  &amp;  3/10  &amp;  7/10\\\\\n0  &amp;  4/10  &amp;  2/10\n\\end{bmatrix}\n\\begin{bmatrix}\n3/10\\\\\n3/10\\\\\n4/10\n\\end{bmatrix}\n=\\begin{bmatrix}\n37/100\\\\\n43/100\\\\\n20/100\n\\end{bmatrix}.\n&lt;/math>\n\nTherefore, starting in state 2, it is '''most likely that after two transitions, the person will still be in state 2''' since 43/100 is the highest of the three probabilities.\n\nNotice, we could also think of the problem as,\n\n:&lt;math>\n\\mathbf{t}_2=P\\mathbf{t}_1=P(P\\mathbf{x})=P^2\\mathbf{x}\n&lt;/math>\n\nso that if we wanted the ''n''&lt;sup>th&lt;/sup> transition probabilities we'd have '''t&lt;sub>n&lt;/sub>''' = ''P&lt;sup>n&lt;/sup>'' '''x'''.\n"
    ], 
    "solvers": [
        "IainMoyles"
    ], 
    "statement_html": "<p>Questions A22-A24 concern a random walk with three states that has transition matrix</p>\n<p><span class=\"math\">\\[\\begin{aligned}\n\\left[\\begin{array}{c c c} 8/10 &amp; 3/10 &amp; 1/10 \\\\ 2/10 &amp; 3/10 &amp; 7/10 \\\\ 0 &amp; 4/10 &amp; 2/10 \\end{array}\\right]\\end{aligned}\\]</span></p>\n<p>If the walker starts in state 2, which state will she most likely be in after 2 time steps?</p>\n", 
    "statement_latex": "Questions A22-A24 concern a random walk with three states that has\ntransition matrix\n\n\\begin{align*}\n\\left[\\begin{array}{c c c} 8/10 & 3/10 & 1/10 \\\\ 2/10 & 3/10 & 7/10 \\\\ 0 & 4/10 & 2/10 \\end{array}\\right]\n\\end{align*}\n\nIf the walker starts in state 2, which state will she most likely be in\nafter 2 time steps?", 
    "statement_raw": "Questions A22-A24 concern a random walk with three states that has transition matrix\n\n:&lt;math>\n\\left[\\begin{array}{c c c} 8/10 &amp; 3/10 &amp; 1/10 \\\\ 2/10 &amp; 3/10 &amp; 7/10 \\\\ 0 &amp; 4/10 &amp; 2/10 \\end{array}\\right]\n&lt;/math>\n\nIf the walker starts in state 2, which state will she most likely be in after 2 time steps?\n", 
    "term": "April", 
    "url": "http://wiki.ubc.ca/Science:Math_Exam_Resources/Courses/MATH152/April_2011/Question_A_23", 
    "year": 2011
}