{
    "answer_html": "<p><strong>So, the answer is (d).</strong></p>\n", 
    "answer_latex": "\\textbf{So, the answer is (d).}", 
    "contributors": [
        "Konradbe", 
        "CarmenBruni"
    ], 
    "course": "MATH103", 
    "flags": [
        "QGQ", 
        "QGH", 
        "QGS", 
        "RT"
    ], 
    "hints_html": [
        "<p>The acceleration <span class=\"math\">\\(a(t)\\)</span> is the second derivative <span class=\"math\">\\(a(t)=x&#39;&#39;(t)\\)</span> of the position <span class=\"math\">\\(x(t)\\)</span>.</p>\n", 
        "<p>With <span class=\"math\">\\(a(t)=x&#39;&#39;(t)\\)</span> we find, that we need to solve the differential equation</p>\n<p><span class=\"math\">\\[\\begin{aligned}\nx&#39;&#39;(t)&amp;=\\cos(t),\\\\\nx&#39;(0)&amp;=0 \\quad\\text{(the molecule rests at time 0)}\\\\\nx(0)&amp;=1\\end{aligned}\\]</span></p>\n"
    ], 
    "hints_latex": [
        "The acceleration $a(t)$ is the second derivative $a(t)=x''(t)$ of the\nposition $x(t)$.", 
        "With $a(t)=x''(t)$ we find, that we need to solve the differential\nequation\n\n\\begin{align*}\nx''(t)&=\\cos(t),\\\\\nx'(0)&=0 \\quad\\text{(the molecule rests at time 0)}\\\\\nx(0)&=1\n\\end{align*}"
    ], 
    "hints_raw": [
        "The acceleration &lt;math> a(t)\\ &lt;/math> is the second derivative &lt;math>\\ a(t)=x''(t)&lt;/math> of the position &lt;math>\\ x(t)&lt;/math>.\n", 
        "With &lt;math>\\ a(t)=x''(t)&lt;/math> we find, that we need to solve the differential equation\n\n&lt;math>\\begin{align}\nx''(t)&amp;=\\cos(t),\\\\\nx'(0)&amp;=0 \\quad\\text{(the molecule rests at time 0)}\\\\\nx(0)&amp;=1\n\\end{align}&lt;/math>\n"
    ], 
    "num_votes": 10, 
    "question": "1 (e)", 
    "rating": 61, 
    "sols_html": [
        "<p>We find, that we need to solve the differential equation</p>\n<p><span class=\"math\">\\[\\begin{aligned}\nx&#39;&#39;(t)&amp;=\\cos(t)\\\\\nx&#39;(0)&amp;=0\\\\\nx(0)&amp;=1\\end{aligned}\\]</span></p>\n<p>We integrate <span class=\"math\">\\(x&#39;&#39;(t)=\\cos(t)\\)</span> and get <span class=\"math\">\\(x&#39;(t)=\\sin(t)+c_1\\)</span>. With <span class=\"math\">\\(0= x&#39;(0)=\\sin(0)+c_1=c_1\\)</span> we find <span class=\"math\">\\(c_1=0\\)</span>.</p>\n<p>We continue with integrating <span class=\"math\">\\(x&#39;(t)=\\sin(t)\\)</span>, which leads to <span class=\"math\">\\(x(t)=-\\cos(t)+c_2\\)</span>. With <span class=\"math\">\\(x(0)=1\\)</span> we find <span class=\"math\">\\(1=x(0)=-\\cos(0)+c_2=-1+c_2\\)</span> and get <span class=\"math\">\\(c_2=2\\)</span>.</p>\n<p>The velocity beeing <span class=\"math\">\\(x&#39;(t)=\\sin(t)\\)</span> reaches <span class=\"math\">\\(-1\\)</span> at <span class=\"math\">\\(t=\\frac{3}{2}\\pi\\)</span>, and we get</p>\n<p><span class=\"math\">\\(x\\left(\\frac{3}{2}\\pi\\right) = -\\cos\\left(\\frac{3}{2}\\pi\\right) + 2 = -0+2=2\\)</span>.</p>\n<p><strong>So, the answer is (d).</strong></p>\n"
    ], 
    "sols_latex": [
        "We find, that we need to solve the differential equation\n\n\\begin{align*}\nx''(t)&=\\cos(t)\\\\\nx'(0)&=0\\\\\nx(0)&=1\n\\end{align*}\n\nWe integrate $x''(t)=\\cos(t)$ and get $x'(t)=\\sin(t)+c_1$. With\n$0= x'(0)=\\sin(0)+c_1=c_1$ we find $c_1=0$.\n\nWe continue with integrating $x'(t)=\\sin(t)$, which leads to\n$x(t)=-\\cos(t)+c_2$. With $x(0)=1$ we find $1=x(0)=-\\cos(0)+c_2=-1+c_2$\nand get $c_2=2$.\n\nThe velocity beeing $x'(t)=\\sin(t)$ reaches $-1$ at $t=\\frac{3}{2}\\pi$,\nand we get\n\n$x\\left(\\frac{3}{2}\\pi\\right) = -\\cos\\left(\\frac{3}{2}\\pi\\right) + 2 = -0+2=2$.\n\n\\textbf{So, the answer is (d).}"
    ], 
    "sols_raw": [
        "We find, that we need to solve the differential equation\n\n&lt;math>\\begin{align}\nx''(t)&amp;=\\cos(t)\\\\\nx'(0)&amp;=0\\\\\nx(0)&amp;=1\n\\end{align}&lt;/math>\n\nWe integrate &lt;math> \\ x''(t)=\\cos(t)&lt;/math> and get &lt;math> x'(t)=\\sin(t)+c_1\\ &lt;/math>.\nWith &lt;math>0= x'(0)=\\sin(0)+c_1=c_1\\ &lt;/math> we find &lt;math> c_1=0\\ &lt;/math>.\n\nWe continue with integrating &lt;math>x'(t)=\\sin(t)\\ &lt;/math>, which leads to &lt;math>\\ x(t)=-\\cos(t)+c_2&lt;/math>.\nWith &lt;math>\\ x(0)=1&lt;/math> we find &lt;math>\\ 1=x(0)=-\\cos(0)+c_2=-1+c_2&lt;/math> and get &lt;math>\\ c_2=2&lt;/math>.\n\nThe velocity beeing &lt;math>\\ x'(t)=\\sin(t)&lt;/math> reaches &lt;math> \\ -1&lt;/math> at &lt;math> t=\\frac{3}{2}\\pi\\ &lt;/math>, and we get\n\n&lt;math>\\ x\\left(\\frac{3}{2}\\pi\\right) = -\\cos\\left(\\frac{3}{2}\\pi\\right) + 2 = -0+2=2&lt;/math>.\n\n'''So, the answer is (d).'''\n"
    ], 
    "solvers": [
        "IsabellGraf"
    ], 
    "statement_html": "<p><em>Multiple Choice question: Select ONE correct answer. You will not be graded for any work.</em></p>\n<p>A charged molecule moves in a changing electric field which results in an acceleration of <em>a(t) = cos(t)</em> (in appropriate units). At time <em>t = 0</em>, the molecule is at rest at position <em>x(0) = 1</em>. What is the position <em>x(t)</em> when the molecule&#8217;s velocity reaches the value -1 for the first time after time 0?</p>\n<p>(a) -1</p>\n<p>(b) 0</p>\n<p>(c) 1</p>\n<p>(d) 2</p>\n<p>(e) The velocity never reaches -1</p>\n", 
    "statement_latex": "\\emph{Multiple Choice question: Select ONE correct answer. You will not\nbe graded for any work.}\n\nA charged molecule moves in a changing electric field which results in\nan acceleration of \\emph{a(t) = cos(t)} (in appropriate units). At time\n\\emph{t = 0}, the molecule is at rest at position \\emph{x(0) = 1}. What\nis the position \\emph{x(t)} when the molecule's velocity reaches the\nvalue -1 for the first time after time 0?\n\n(a) -1\n\n(b) 0\n\n(c) 1\n\n(d) 2\n\n(e) The velocity never reaches -1", 
    "statement_raw": "''Multiple Choice question: Select ONE correct answer. You will not be graded for any work.''\n\nA charged molecule moves in a changing electric field which results in an acceleration of ''a(t) = cos(t)'' (in appropriate units). At time ''t = 0'', the molecule is at rest at position ''x(0) = 1''. What is the position ''x(t)'' when the molecule's velocity reaches the value -1 for the first time after time 0?\n\n(a) -1\n\n(b) 0 \n\n(c) 1\n\n(d) 2\n\n(e) The velocity never reaches -1\n", 
    "term": "April", 
    "topics": [
        "Differential_equation", 
        "Net_change_theorem"
    ], 
    "url": "http://wiki.ubc.ca/Science:Math_Exam_Resources/Courses/MATH103/April_2009/Question_01_(e)", 
    "year": 2009
}