{
    "answer_html": "<p><span class=\"math\">\\(u(t)=\\frac{1}{2} \\sin(5t) - \\frac{5}{4} e^{-3t} \\sin(4t) + e^{-3t} \\cos(4t).\\)</span></p>\n", 
    "answer_latex": " $u(t)=\\frac{1}{2} \\sin(5t) - \\frac{5}{4} e^{-3t} \\sin(4t) + e^{-3t} \\cos(4t).$ ", 
    "contributors": [
        "DavidKohler", 
        "Konradbe", 
        "IainMoyles", 
        "ChristinaKoch"
    ], 
    "course": "MATH215", 
    "flags": [
        "QGQ", 
        "QGH", 
        "QGS", 
        "CT"
    ], 
    "hints_html": [
        "<p>What are the particular and homogeneous solutions?</p>\n"
    ], 
    "hints_latex": [
        "What are the particular and homogeneous solutions?"
    ], 
    "hints_raw": [
        "What are the particular and homogeneous solutions?\n"
    ], 
    "num_votes": 3, 
    "question": "4 (b)", 
    "rating": 30, 
    "sols_html": [
        "<p>Notice that the ODE</p>\n<p><span class=\"math\">\\[\\begin{aligned}\n\\displaystyle{}u&#39;&#39; + 6u&#39; + 25u = 15 \\cos(5t)\\end{aligned}\\]</span></p>\n<p>has a nonzero right-hand side. We will begin by solving the homogeneous equation</p>\n<p><span class=\"math\">\\[\\begin{aligned}\n\\displaystyle{}u&#39;&#39; + 6u&#39; + 25u = 0.\\end{aligned}\\]</span></p>\n<p>By making the ansatz <span class=\"math\">\\(u = \\exp(rt)\\)</span> we arrive at</p>\n<p><span class=\"math\">\\[\\begin{aligned}\n\\displaystyle{}r^2 + 6r + 25 = 0\\end{aligned}\\]</span></p>\n<p>with roots <span class=\"math\">\\(r = -3 \\pm 4 i\\)</span>. Complex roots of the form <span class=\"math\">\\(a+ib\\)</span> lead to solutions of the form</p>\n<p><span class=\"math\">\\[\\begin{aligned}\n&amp;e^{at}\\sin(bt)\\\\\n&amp;e^{at}\\cos(bt).\\end{aligned}\\]</span></p>\n<p>Therefore the homogeneous solution is</p>\n<p><span class=\"math\">\\[\\begin{aligned}\n\\displaystyle{}u_h = C_1 e^{-3t} \\sin(4t) + C_2 e^{-3t} \\cos(4t).\\end{aligned}\\]</span></p>\n<p>The right-hand side is sinusoidal with argument <span class=\"math\">\\(5t\\)</span>. We need to think of which functions (and their derivatives) that could lead to this possible right-hand side. The only such possible functions are</p>\n<p><span class=\"math\">\\[\\begin{aligned}\n\\cos(5t)\\\\\n\\sin(5t)\\end{aligned}\\]</span></p>\n<p>and so, we will find a particular solution of the form</p>\n<p><span class=\"math\">\\[\\begin{aligned}\n\\displaystyle{}u_p = A \\sin(5t) + B \\cos(5t).\\end{aligned}\\]</span></p>\n<p>Taking this particular solution and plugging it in to the ODE, we have:</p>\n<p><span class=\"math\">\\[\\begin{aligned}\n(-25 A \\sin(5t) - 25 B \\cos(5t)) + 6(5 A \\cos(5t) - 5B \\sin(5t)) + 25(A \\sin(5t) + B \\cos(5t)) &amp;= 15 \\cos(5t)\n\\\\ -30B \\sin(5t) + 30A \\cos(5t) &amp;= 15 \\cos(5t)\\end{aligned}\\]</span></p>\n<p>In comparing the coefficients of <span class=\"math\">\\(\\sin(5t)\\)</span> and <span class=\"math\">\\(\\cos(5t)\\)</span>, we find that</p>\n<p><span class=\"math\">\\[\\begin{aligned}\nB &amp;= 0\\\\\nA &amp;= 1/2.\\end{aligned}\\]</span></p>\n<p>The general solution to the ODE will be <span class=\"math\">\\(u = u_h + u_p\\)</span>, giving</p>\n<p><span class=\"math\">\\[\\begin{aligned}\nu = \\frac{1}{2} \\sin(5t) + C_1 e^{-3t} \\sin(4t) + C_2 e^{-3t} \\cos(4t).\\end{aligned}\\]</span></p>\n<p>The initial conditions tell us</p>\n<p><span class=\"math\">\\[\\begin{aligned}\nu(0)&amp;=1\\\\\nu&#39;(0)&amp;=-\\frac{11}{2}\\end{aligned}\\]</span></p>\n<p>From this, we have,</p>\n<p><span class=\"math\">\\[\\begin{aligned}\n\\displaystyle{}u(0) = C_2 = 1\\end{aligned}\\]</span></p>\n<p>and</p>\n<p><span class=\"math\">\\[\\begin{aligned}\nu&#39;(0) = \\left.\\left(\\frac{5}{2} \\cos(5t) - 3 C_1 e^{-3t} \\sin(4t) + 4 C_1 e^{-3t} \\cos(4t) - 3 C_2 e^{-3t} \\cos(4t) - 4 C_2 e^{-3t} \\sin(4t)\\right)\\right|_{t=0} = \\frac{5}{2} + 4 C_1 - 3 = \\frac{-11}{2}.\\end{aligned}\\]</span></p>\n<p>Therefore we get that</p>\n<p><span class=\"math\">\\[\\begin{aligned}\n\\displaystyle{}C_1 = -5/4.\\end{aligned}\\]</span></p>\n<p>The solution is thus</p>\n<p><span class=\"math\">\\[\\begin{aligned}\nu(t) = \\frac{1}{2} \\sin(5t) - \\frac{5}{4} e^{-3t} \\sin(4t) + e^{-3t} \\cos(4t).\\end{aligned}\\]</span></p>\n"
    ], 
    "sols_latex": [
        "Notice that the ODE\n\n\\begin{align*}\n\\displaystyle{}u'' + 6u' + 25u = 15 \\cos(5t)\n\\end{align*}\n\nhas a nonzero right-hand side. We will begin by solving the homogeneous\nequation\n\n\\begin{align*}\n\\displaystyle{}u'' + 6u' + 25u = 0.\n\\end{align*}\n\nBy making the ansatz $u = \\exp(rt)$ we arrive at\n\n\\begin{align*}\n\\displaystyle{}r^2 + 6r + 25 = 0\n\\end{align*}\n\nwith roots $r = -3 \\pm 4 i$. Complex roots of the form $a+ib$ lead to\nsolutions of the form\n\n\\begin{align*}\n&e^{at}\\sin(bt)\\\\\n&e^{at}\\cos(bt).\n\\end{align*}\n\nTherefore the homogeneous solution is\n\n\\begin{align*}\n\\displaystyle{}u_h = C_1 e^{-3t} \\sin(4t) + C_2 e^{-3t} \\cos(4t).\n\\end{align*}\n\nThe right-hand side is sinusoidal with argument $5t$. We need to think\nof which functions (and their derivatives) that could lead to this\npossible right-hand side. The only such possible functions are\n\n\\begin{align*}\n\\cos(5t)\\\\\n\\sin(5t)\n\\end{align*}\n\nand so, we will find a particular solution of the form\n\n\\begin{align*}\n\\displaystyle{}u_p = A \\sin(5t) + B \\cos(5t).\n\\end{align*}\n\nTaking this particular solution and plugging it in to the ODE, we have:\n\n\\begin{align*}\n(-25 A \\sin(5t) - 25 B \\cos(5t)) + 6(5 A \\cos(5t) - 5B \\sin(5t)) + 25(A \\sin(5t) + B \\cos(5t)) &= 15 \\cos(5t)\n\\\\ -30B \\sin(5t) + 30A \\cos(5t) &= 15 \\cos(5t)\n\\end{align*}\n\nIn comparing the coefficients of $\\sin(5t)$ and $\\cos(5t)$, we find that\n\n\\begin{align*}\nB &= 0\\\\\nA &= 1/2.\n\\end{align*}\n\nThe general solution to the ODE will be $u = u_h + u_p$, giving\n\n\\begin{align*}\nu = \\frac{1}{2} \\sin(5t) + C_1 e^{-3t} \\sin(4t) + C_2 e^{-3t} \\cos(4t).\n\\end{align*}\n\nThe initial conditions tell us\n\n\\begin{align*}\nu(0)&=1\\\\\nu'(0)&=-\\frac{11}{2}\n\\end{align*}\n\nFrom this, we have,\n\n\\begin{align*}\n\\displaystyle{}u(0) = C_2 = 1\n\\end{align*}\n\nand\n\n\\begin{align*}\nu'(0) = \\left.\\left(\\frac{5}{2} \\cos(5t) - 3 C_1 e^{-3t} \\sin(4t) + 4 C_1 e^{-3t} \\cos(4t) - 3 C_2 e^{-3t} \\cos(4t) - 4 C_2 e^{-3t} \\sin(4t)\\right)\\right|_{t=0} = \\frac{5}{2} + 4 C_1 - 3 = \\frac{-11}{2}.\n\\end{align*}\n\nTherefore we get that\n\n\\begin{align*}\n\\displaystyle{}C_1 = -5/4.\n\\end{align*}\n\nThe solution is thus\n\n\\begin{align*}\nu(t) = \\frac{1}{2} \\sin(5t) - \\frac{5}{4} e^{-3t} \\sin(4t) + e^{-3t} \\cos(4t).\n\\end{align*}"
    ], 
    "sols_raw": [
        "Notice that the ODE\n\n:&lt;math>\n\\displaystyle{}u'' + 6u' + 25u = 15 \\cos(5t)\n&lt;/math>\n\nhas a nonzero right-hand side. We will begin by solving the homogeneous equation\n\n:&lt;math>\n\\displaystyle{}u'' + 6u' + 25u = 0.\n&lt;/math>\n\nBy making the ansatz &lt;math>u = \\exp(rt)&lt;/math> we arrive at\n\n:&lt;math>\n\\displaystyle{}r^2 + 6r + 25 = 0\n&lt;/math>\n\nwith roots &lt;math>r = -3 \\pm 4 i&lt;/math>. Complex roots of the form &lt;math>a+ib&lt;/math> lead to solutions of the form\n\n:&lt;math>\n\\begin{align}\n&amp;e^{at}\\sin(bt)\\\\\n&amp;e^{at}\\cos(bt).\n\\end{align}\n&lt;/math>\n\nTherefore the homogeneous solution is\n\n:&lt;math>\n\\displaystyle{}u_h = C_1 e^{-3t} \\sin(4t) + C_2 e^{-3t} \\cos(4t).\n&lt;/math>\n\nThe right-hand side is sinusoidal with argument &lt;math>5t&lt;/math>.  We need to think of which functions (and their derivatives) that could lead to this possible right-hand side.  The only such possible functions are\n\n:&lt;math>\n\\begin{align}\n\\cos(5t)\\\\\n\\sin(5t)\n\\end{align}\n&lt;/math>\n\nand so, we will find a particular solution of the form\n\n:&lt;math>\n\\displaystyle{}u_p = A \\sin(5t) + B \\cos(5t).\n&lt;/math>\n\nTaking this particular solution and plugging it in to the ODE, we have:\n\n:&lt;math>\n\\begin{align}\n(-25 A \\sin(5t) - 25 B \\cos(5t)) + 6(5 A \\cos(5t) - 5B \\sin(5t)) + 25(A \\sin(5t) + B \\cos(5t)) &amp;= 15 \\cos(5t)\n\\\\ -30B \\sin(5t) + 30A \\cos(5t) &amp;= 15 \\cos(5t)\n\\end{align}\n&lt;/math>\n\nIn comparing the coefficients of &lt;math>\\sin(5t)&lt;/math> and &lt;math>\\cos(5t)&lt;/math>, we find that \n\n:&lt;math>\n\\begin{align}\nB &amp;= 0\\\\\nA &amp;= 1/2.\n\\end{align}\n&lt;/math>\n\nThe general solution to the ODE will be &lt;math>u = u_h + u_p&lt;/math>, giving\n\n:&lt;math>\nu = \\frac{1}{2} \\sin(5t) + C_1 e^{-3t} \\sin(4t) + C_2 e^{-3t} \\cos(4t).\n&lt;/math>\n\nThe initial conditions tell us\n\n:&lt;math>\n\\begin{align}\nu(0)&amp;=1\\\\\nu'(0)&amp;=-\\frac{11}{2}\n\\end{align}\n&lt;/math>\n\nFrom this, we have, \n\n:&lt;math>\n\\displaystyle{}u(0) = C_2 = 1\n&lt;/math>\n\nand \n\n:&lt;math>\nu'(0) = \\left.\\left(\\frac{5}{2} \\cos(5t) - 3 C_1 e^{-3t} \\sin(4t) + 4 C_1 e^{-3t} \\cos(4t) - 3 C_2 e^{-3t} \\cos(4t) - 4 C_2 e^{-3t} \\sin(4t)\\right)\\right|_{t=0} = \\frac{5}{2} + 4 C_1 - 3 = \\frac{-11}{2}.\n&lt;/math>\n\nTherefore we get that\n\n:&lt;math>\n\\displaystyle{}C_1 = -5/4.\n&lt;/math>\n\nThe solution is thus\n\n:&lt;math>\nu(t) = \\frac{1}{2} \\sin(5t) - \\frac{5}{4} e^{-3t} \\sin(4t) + e^{-3t} \\cos(4t).\n&lt;/math>\n"
    ], 
    "solvers": [
        "MikeL"
    ], 
    "statement_html": "<p>Suppose the motion of a spring-mass system is described by the following differential equation</p>\n<p><span class=\"math\">\\[\\begin{aligned}\n2u&#39;&#39; + 2\\gamma u&#39; + 18u = 0, \\quad u(0) = 1, u&#39;(0) = -\\frac{11}2\\end{aligned}\\]</span></p>\n<p><strong>(b)</strong> Solve the following equation for <em>u</em>(<em>t</em>) in explicit form.</p>\n<p><span class=\"math\">\\[\\begin{aligned}\nu&#39;&#39; + 6u&#39; + 25u = 15\\cos(5t), \\quad u(0) = 1, u&#39;(0) = -\\frac{11}2\\end{aligned}\\]</span></p>\n", 
    "statement_latex": "Suppose the motion of a spring-mass system is described by the following\ndifferential equation\n\n\\begin{align*}\n2u'' + 2\\gamma u' + 18u = 0, \\quad u(0) = 1, u'(0) = -\\frac{11}2\n\\end{align*}\n\n\\textbf{(b)} Solve the following equation for \\emph{u}(\\emph{t}) in\nexplicit form.\n\n\\begin{align*}\nu'' + 6u' + 25u = 15\\cos(5t), \\quad u(0) = 1, u'(0) = -\\frac{11}2\n\\end{align*}", 
    "statement_raw": "Suppose the motion of a spring-mass system is described by the following differential equation\n\n:&lt;math>\n2u'' + 2\\gamma u' + 18u = 0, \\quad u(0) = 1, u'(0) = -\\frac{11}2\n&lt;/math>\n\n'''(b)''' Solve the following equation for ''u''(''t'') in explicit form.\n\n:&lt;math>\nu'' + 6u' + 25u = 15\\cos(5t), \\quad u(0) = 1, u'(0) = -\\frac{11}2\n&lt;/math>\n", 
    "term": "December", 
    "url": "http://wiki.ubc.ca/Science:Math_Exam_Resources/Courses/MATH215/December_2011/Question_04_(b)", 
    "year": 2011
}