{
    "answer_html": "<p>And all of these are true since <span class=\"math\">\\(\\displaystyle 1728 = 2^{6}3^{3}\\)</span>.Hence 1729 is a Carmichael number.</p>\n", 
    "answer_latex": "And all of these are true since\n$\\displaystyle 1728 = 2^{6}3^{3}$.Hence 1729 is a Carmichael\nnumber.", 
    "contributors": [
        "Konradbe"
    ], 
    "course": "MATH312", 
    "flags": [
        "QGQ", 
        "RH", 
        "RS", 
        "RT"
    ], 
    "hints_html": [
        "<p>A Carmichael number is a composite number <em>n</em> which satisfies</p>\n<p><span class=\"math\">\\(\\displaystyle b^{n-1} \\equiv 1 \\mod{n}\\)</span></p>\n<p>for all integers with <span class=\"math\">\\(\\displaystyle \\gcd(b,n) = 1\\)</span>.</p>\n", 
        "<p>Recall Korselt&#8217;s criterion which states that a positive composite integer <em>n</em> is a Carmichael number if and only if <em>n</em> is square free and for all prime divisors <em>p</em> of <em>n</em>, it is true that <span class=\"math\">\\(\\displaystyle (p-1) \\mid (n-1)\\)</span></p>\n"
    ], 
    "hints_latex": [
        "A Carmichael number is a composite number \\emph{n} which satisfies\n\n$\\displaystyle b^{n-1} \\equiv 1 \\mod{n}$\n\nfor all integers with $\\displaystyle \\gcd(b,n) = 1$.", 
        "Recall Korselt's criterion which states that a positive composite\ninteger \\emph{n} is a Carmichael number if and only if \\emph{n} is\nsquare free and for all prime divisors \\emph{p} of \\emph{n}, it is true\nthat $\\displaystyle (p-1) \\mid (n-1)$"
    ], 
    "hints_raw": [
        "A Carmichael number is a composite number ''n'' which satisfies \n\n&lt;math> \\displaystyle b^{n-1} \\equiv 1 \\mod{n}&lt;/math>\n\nfor all integers with &lt;math> \\displaystyle \\gcd(b,n) = 1&lt;/math>.\n", 
        "Recall Korselt's criterion which states that a positive composite integer ''n'' is a Carmichael number if and only if ''n'' is square free and for all prime divisors ''p'' of ''n'', it is true that &lt;math> \\displaystyle (p-1) \\mid (n-1)&lt;/math>\n"
    ], 
    "num_votes": 0, 
    "question": "4 (b)", 
    "rating": null, 
    "sols_html": [
        "<p>We proceed using the hints. Clearly 1729 is square free so it suffices to check that for each prime divisor, we have that <span class=\"math\">\\((p-1)\\mid(n-1)\\)</span>. We proceed mechanically</p>\n<p><span class=\"math\">\\[\\begin{aligned}\n(7-1) &amp;= 6 \\mid 1728 \\\\\n(13-1) &amp;= 12 \\mid 1728 \\\\\n(19-1) &amp;= 18 \\mid 1728 \\end{aligned}\\]</span></p>\n<p>And all of these are true since <span class=\"math\">\\(\\displaystyle 1728 = 12^{3} = 2^{6}3^{3}\\)</span>. Hence 1729 is a Carmichael number.</p>\n"
    ], 
    "sols_latex": [
        "We proceed using the hints. Clearly 1729 is square free so it suffices\nto check that for each prime divisor, we have that $(p-1)\\mid(n-1)$. We\nproceed mechanically\n\n\\begin{align*}\n(7-1) &= 6 \\mid 1728 \\\\\n(13-1) &= 12 \\mid 1728 \\\\\n(19-1) &= 18 \\mid 1728 \n\\end{align*}\n\nAnd all of these are true since\n$\\displaystyle 1728 = 12^{3} = 2^{6}3^{3}$. Hence 1729 is a Carmichael\nnumber."
    ], 
    "sols_raw": [
        "We proceed using the hints. Clearly 1729 is square free so it suffices to check that for each prime divisor, we have that &lt;math>(p-1)\\mid(n-1) &lt;/math>. We proceed mechanically\n\n&lt;math>\n\\begin{align}\n(7-1) &amp;= 6 \\mid 1728 \\\\\n(13-1) &amp;= 12 \\mid 1728 \\\\\n(19-1) &amp;= 18 \\mid 1728 \n\\end{align}\n&lt;/math>\n\nAnd all of these are true since &lt;math> \\displaystyle 1728 = 12^{3} = 2^{6}3^{3}&lt;/math>. Hence 1729 is a Carmichael number.\n"
    ], 
    "solvers": [
        "CarmenBruni"
    ], 
    "statement_html": "<p>Prove that <span class=\"math\">\\(\\displaystyle 1729 = 7 \\cdot 13 \\cdot 19\\)</span> is a Carmichael number.</p>\n<p>(Hint</p>\n<p><span class=\"math\">\\[\\begin{aligned}\n\\displaystyle 1728 = 6 \\cdot 288 = 12 \\cdot 144 = 18 \\cdot 96\\end{aligned}\\]</span></p>\n<p>)</p>\n", 
    "statement_latex": "Prove that $\\displaystyle 1729 = 7 \\cdot 13 \\cdot 19$ is a Carmichael\nnumber.\n\n(Hint\\begin{align*}\n\\displaystyle 1728 = 6 \\cdot 288 = 12 \\cdot 144 = 18 \\cdot 96\n\\end{align*})", 
    "statement_raw": "Prove that &lt;math> \\displaystyle 1729 = 7 \\cdot 13 \\cdot 19&lt;/math> is a Carmichael number. \n\n(Hint: &lt;math> \\displaystyle 1728 = 6 \\cdot 288 = 12 \\cdot 144 = 18 \\cdot 96&lt;/math>)\n", 
    "term": "December", 
    "topics": [
        "Carmichael_number"
    ], 
    "url": "http://wiki.ubc.ca/Science:Math_Exam_Resources/Courses/MATH312/December_2008/Question_04_(b)", 
    "year": 2008
}