{
    "answer_html": "<p><span class=\"math\">\\(\\begin{array}{rcl}\n36 &amp;&lt; 48 &amp;&lt; 49 \\\\\n\\sqrt{36} &amp;&lt; \\sqrt{48} &amp;&lt; \\sqrt{49} \\\\\n6 &amp;&lt; b &amp;&lt; 7 \\end{array}\\)</span></p>\n", 
    "answer_latex": "$\\begin{array}{rcl}\n36 &< 48 &< 49 \\\\\n\\sqrt{36} &< \\sqrt{48} &< \\sqrt{49} \\\\\n6 &< b &< 7 \\end{array}$", 
    "contributors": [
        "Konradbe"
    ], 
    "course": "MATH102", 
    "flags": [
        "QGQ", 
        "QGH", 
        "QGS", 
        "CT"
    ], 
    "hints_html": [
        "<p>Which numbers near 48 are perfect squares? What are their square roots?</p>\n"
    ], 
    "hints_latex": [
        "Which numbers near 48 are perfect squares? What are their square roots?"
    ], 
    "hints_raw": [
        "Which numbers near 48 are perfect squares?  What are their square roots?\n"
    ], 
    "num_votes": 0, 
    "question": "C 03 (a)", 
    "rating": null, 
    "sols_html": [
        "<p>The number 48 is between perfect squares 36 and 49, so we have:</p>\n<p><span class=\"math\">\\(\\begin{array}{rcl}\n36 &amp;&lt; 48 &amp;&lt; 49 \\\\\n\\sqrt{36} &amp;&lt; \\sqrt{48} &amp;&lt; \\sqrt{49} \\\\\n6 &amp;&lt; b &amp;&lt; 7 \\end{array}\\)</span></p>\n"
    ], 
    "sols_latex": [
        "The number 48 is between perfect squares 36 and 49, so we have:\n\n$\\begin{array}{rcl}\n36 &< 48 &< 49 \\\\\n\\sqrt{36} &< \\sqrt{48} &< \\sqrt{49} \\\\\n6 &< b &< 7 \\end{array}$"
    ], 
    "sols_raw": [
        "The number 48 is between perfect squares 36 and 49, so we have:\n\n&lt;math> \\begin{array}{rcl}\n36 &amp;&lt; 48 &amp;&lt; 49 \\\\\n\\sqrt{36} &amp;&lt; \\sqrt{48} &amp;&lt; \\sqrt{49} \\\\\n6 &amp;&lt; b &amp;&lt; 7 \\end{array}&lt;/math>\n"
    ], 
    "solvers": [
        "ChristinaKoch"
    ], 
    "statement_html": "<p>This question is about approximating the value of <span class=\"math\">\\(b = \\sqrt{48}\\)</span>.</p>\n<p><strong>(a)</strong> Between which two successive integers does <em>b</em> lie?</p>\n", 
    "statement_latex": "This question is about approximating the value of $b = \\sqrt{48}$.\n\n\\textbf{(a)} Between which two successive integers does \\emph{b} lie?", 
    "statement_raw": "This question is about approximating the value of &lt;math> b = \\sqrt{48} &lt;/math>.\n\n'''(a)''' Between which two successive integers does ''b'' lie?\n", 
    "term": "December", 
    "url": "http://wiki.ubc.ca/Science:Math_Exam_Resources/Courses/MATH102/December_2012/Question_C_03_(a)", 
    "year": 2012
}